eshop_cart/__init__.py
eshop_cart/utils.py
eshop_cart-1.0.0.dist-info/LICENCE
eshop_cart-1.0.0.dist-info/METADATA
eshop_cart-1.0.0.dist-info/WHEEL
eshop_cart-1.0.0.dist-info/top_level.txt
eshop_cart-1.0.0.dist-info/RECORD
