Metadata-Version: 2.1
Name: eshop_cart
Version: 1.0.0
Summary: E-shop cart
Author-email: Silicus <x20131640@student.ncirl.ie>
Project-URL: Homepage, https://github.com/pypa/sampleproject
Project-URL: Bug Tracker, https://github.com/pypa/sampleproject/issues
Classifier: Programming Language :: Python :: 3
Classifier: License :: OSI Approved :: MIT License
Classifier: Operating System :: OS Independent
Requires-Python: >=3.7
License-File: LICENCE
